README.rst
britney_http_signature.py
setup.py
britney_http_signature.egg-info/PKG-INFO
britney_http_signature.egg-info/SOURCES.txt
britney_http_signature.egg-info/dependency_links.txt
britney_http_signature.egg-info/entry_points.txt
britney_http_signature.egg-info/requires.txt
britney_http_signature.egg-info/top_level.txt