Metadata-Version: 1.1
Name: britney-http-signature
Version: 0.1
Summary: Http Signature authenticatio middleware for britney
Home-page: https://github.com/agrausem/britney-http-signature
Author: Arnaud Grausem
Author-email: arnaud.grausem@gmail.com
License: PSF
Download-URL: http://pypi.python.org/pypi/britney-http-signature
Keywords: SPORE,REST Api,authentication,britney,http signature
Platform: UNKNOWN
Classifier: Development Status :: 4 - Beta
Classifier: Environment :: Web Environment
Classifier: Intended Audience :: Developers
Classifier: License :: OSI Approved :: BSD License
Classifier: Operating System :: OS Independent
Classifier: Programming Language :: Python :: 2.7
Classifier: Programming Language :: Python :: 3.2
Classifier: Programming Language :: Python :: 3.3
